fileunity_seqreads/__init__.py
fileunity_seqreads-0.1.1.dist-info/LICENSE.txt
fileunity_seqreads-0.1.1.dist-info/METADATA
fileunity_seqreads-0.1.1.dist-info/WHEEL
fileunity_seqreads-0.1.1.dist-info/top_level.txt
fileunity_seqreads-0.1.1.dist-info/RECORD
