Metadata-Version: 2.1
Name: fileunity-seqreads
Version: 0.1.1
Summary: fileunity for seqreads
Author-email: Johannes <johannes-programming@posteo.org>
License: The MIT License (MIT)
Project-URL: Download, https://pypi.org/project/fileunity-seqreads/#files
Project-URL: Source, https://github.com/johannes-programming/fileunity_seqreads
Classifier: License :: OSI Approved :: MIT License
Classifier: Programming Language :: Python
Classifier: Programming Language :: Python :: 3
Requires-Python: >=3.11
License-File: LICENSE.txt
Requires-Dist: Bio >=1.6
Requires-Dist: fileunity >=1.3
Requires-Dist: seqreads >=0.1
